LICENCE
gcages-0.12.0.dist-info/METADATA
gcages-0.12.0.dist-info/WHEEL
gcages-0.12.0.dist-info/entry_points.txt
gcages-0.12.0.dist-info/licenses/LICENCE
gcages/__init__.py
gcages/aggregation.py
gcages/aneris_helpers.py
gcages/ar6/__init__.py
gcages/ar6/harmonisation.py
gcages/ar6/infilling.py
gcages/ar6/post_processing.py
gcages/ar6/pre_processing.py
gcages/ar6/scm_running.py
gcages/assertions.py
gcages/cmip7_scenariomip/__init__.py
gcages/cmip7_scenariomip/gridding_emissions.py
gcages/cmip7_scenariomip/pre_processing/__init__.py
gcages/cmip7_scenariomip/pre_processing/pre_processor.py
gcages/cmip7_scenariomip/pre_processing/reaggregation/__init__.py
gcages/cmip7_scenariomip/pre_processing/reaggregation/basic.py
gcages/cmip7_scenariomip/pre_processing/reaggregation/common.py
gcages/completeness.py
gcages/databases/__init__.py
gcages/databases/emissions_variables.py
gcages/exceptions.py
gcages/harmonisation/__init__.py
gcages/harmonisation/aneris.py
gcages/harmonisation/common.py
gcages/hashing.py
gcages/index_manipulation.py
gcages/internal_consistency.py
gcages/post_processing.py
gcages/py.typed
gcages/renaming.py
gcages/scm_running.py
gcages/testing.py
gcages/typing.py
gcages/units_helpers.py
gcages-0.12.0.dist-info/RECORD
