Metadata-Version: 2.1
Name: gcages
Version: 0.12.0
Summary: Global Climate Assessment of Global Emission Scenarios, typically (but not always) produced by Integrated Assessment Models (IAMs).
Author-Email: Zebedee Nicholls <zebedee.nicholls@climate-resource.com>
License: 3-Clause BSD License
Classifier: Development Status :: 3 - Alpha
Classifier: Intended Audience :: Science/Research
Classifier: License :: OSI Approved :: BSD License
Classifier: Natural Language :: English
Classifier: Operating System :: OS Independent
Classifier: Programming Language :: Python
Classifier: Programming Language :: Python :: 3
Classifier: Programming Language :: Python :: 3 :: Only
Classifier: Programming Language :: Python :: 3.9
Classifier: Programming Language :: Python :: 3.10
Classifier: Programming Language :: Python :: 3.11
Classifier: Programming Language :: Python :: 3.12
Classifier: Programming Language :: Python :: 3.13
Classifier: Typing :: Typed
Project-URL: Homepage, https://gcages.readthedocs.io
Project-URL: Documentation, https://gcages.readthedocs.io
Project-URL: Changelog, https://gcages.readthedocs.io/en/stable/changelog
Project-URL: Repository, https://github.com/openscm/gcages
Project-URL: Issues, https://github.com/openscm/gcages/issues
Requires-Python: >=3.9
Requires-Dist: backports-strenum>=1.3.1; python_version < "3.11"
Requires-Dist: numpy>=1.26.0; python_version < "3.13"
Requires-Dist: numpy>=2.1.0; python_version >= "3.13"
Requires-Dist: pandas>=2.2.0
Requires-Dist: pandas-openscm>=0.5.1
Provides-Extra: ar6
Requires-Dist: aneris-iamc>=0.4.2; python_version >= "3.10" and extra == "ar6"
Requires-Dist: pycountry>=24.0; python_version >= "3.10" and extra == "ar6"
Requires-Dist: importlib-resources>=5.0; python_version >= "3.10" and python_version <= "3.11" and extra == "ar6"
Requires-Dist: openscm-runner>=0.13.0; extra == "ar6"
Requires-Dist: pandas-indexing[units]>=0.6.3; extra == "ar6"
Requires-Dist: pandas-openscm[db]>=0.5.1; extra == "ar6"
Requires-Dist: pymagicc>=2.1.5; extra == "ar6"
Requires-Dist: scipy>=1.13.0; extra == "ar6"
Requires-Dist: scmdata>=0.18.0; extra == "ar6"
Requires-Dist: silicone>=1.3.0; extra == "ar6"
Provides-Extra: cmip7scenariomip
Requires-Dist: pandas-indexing>=0.6.3; extra == "cmip7scenariomip"
Provides-Extra: progress
Requires-Dist: tqdm>=4.0.0; extra == "progress"
Provides-Extra: full
Requires-Dist: gcages[ar6]; extra == "full"
Requires-Dist: gcages[cmip7scenariomip]; extra == "full"
Requires-Dist: gcages[progress]; extra == "full"
Provides-Extra: locked
Requires-Dist: attrs==24.3.0; extra == "locked"
Requires-Dist: backports-strenum==1.3.1; python_version >= "3.9" and python_version < "3.11" and extra == "locked"
Requires-Dist: numpy==2.2.6; python_version >= "3.10" and python_version < "3.12" and extra == "locked"
Requires-Dist: numpy==2.3.3; python_version >= "3.12" and extra == "locked"
Requires-Dist: numpy==2.0.2; python_version < "3.10" and python_version >= "3.9" and extra == "locked"
Requires-Dist: pandas==2.3.3; extra == "locked"
Requires-Dist: pandas-openscm==0.9.0; extra == "locked"
Requires-Dist: python-dateutil==2.9.0.post0; extra == "locked"
Requires-Dist: pytz==2025.2; extra == "locked"
Requires-Dist: six==1.17.0; extra == "locked"
Requires-Dist: tzdata==2025.2; extra == "locked"
Provides-Extra: ar6-locked
Requires-Dist: alembic==1.16.5; python_version >= "3.10" and python_version < "3.13" and extra == "ar6-locked"
Requires-Dist: aneris-iamc==0.4.2; python_version >= "3.10" and extra == "ar6-locked"
Requires-Dist: annotated-types==0.7.0; python_version >= "3.10" and python_version < "3.13" and extra == "ar6-locked"
Requires-Dist: anyio==4.8.0; extra == "ar6-locked"
Requires-Dist: attrs==24.3.0; extra == "ar6-locked"
Requires-Dist: certifi==2024.12.14; extra == "ar6-locked"
Requires-Dist: cftime==1.6.4.post1; extra == "ar6-locked"
Requires-Dist: charset-normalizer==3.4.1; extra == "ar6-locked"
Requires-Dist: click==8.1.8; extra == "ar6-locked"
Requires-Dist: colorama==0.4.6; extra == "ar6-locked"
Requires-Dist: contourpy==1.3.2; python_version >= "3.10" and python_version < "3.12" and extra == "ar6-locked"
Requires-Dist: contourpy==1.3.3; python_version >= "3.12" and extra == "ar6-locked"
Requires-Dist: contourpy==1.3.0; python_version < "3.10" and python_version >= "3.9" and extra == "ar6-locked"
Requires-Dist: cycler==0.12.1; extra == "ar6-locked"
Requires-Dist: deprecated==1.2.18; extra == "ar6-locked"
Requires-Dist: et-xmlfile==2.0.0; extra == "ar6-locked"
Requires-Dist: exceptiongroup==1.3.0; python_version >= "3.9" and python_version < "3.11" and extra == "ar6-locked"
Requires-Dist: f90nml==1.5; extra == "ar6-locked"
Requires-Dist: fastapi==0.118.3; python_version >= "3.10" and python_version < "3.13" and extra == "ar6-locked"
Requires-Dist: filelock==3.20.0; python_version >= "3.10" and extra == "ar6-locked"
Requires-Dist: filelock==3.19.1; python_version < "3.10" and python_version >= "3.9" and extra == "ar6-locked"
Requires-Dist: flexcache==0.3; extra == "ar6-locked"
Requires-Dist: flexparser==0.4; extra == "ar6-locked"
Requires-Dist: fonttools==4.60.1; extra == "ar6-locked"
Requires-Dist: globalwarmingpotentials==0.11.1; extra == "ar6-locked"
Requires-Dist: greenlet==3.2.4; python_version >= "3.10" and python_version < "3.13" and (platform_machine == "win32" or platform_machine == "WIN32" or platform_machine == "AMD64" or platform_machine == "amd64" or platform_machine == "x86_64" or platform_machine == "ppc64le" or platform_machine == "aarch64") and extra == "ar6-locked"
Requires-Dist: h11==0.14.0; extra == "ar6-locked"
Requires-Dist: h2==4.3.0; python_version >= "3.9" and python_version < "3.13" and extra == "ar6-locked"
Requires-Dist: hpack==4.1.0; python_version >= "3.9" and python_version < "3.13" and extra == "ar6-locked"
Requires-Dist: httpcore==1.0.7; extra == "ar6-locked"
Requires-Dist: httpx==0.28.1; extra == "ar6-locked"
Requires-Dist: httpx[http2]==0.28.1; python_version >= "3.9" and python_version < "3.13" and extra == "ar6-locked"
Requires-Dist: hyperframe==6.1.0; python_version >= "3.9" and python_version < "3.13" and extra == "ar6-locked"
Requires-Dist: iam-units==2025.9.12; extra == "ar6-locked"
Requires-Dist: idna==3.10; extra == "ar6-locked"
Requires-Dist: importlib-metadata==8.7.0; (python_version < "3.10" and python_version >= "3.9" or python_version >= "3.13") and extra == "ar6-locked"
Requires-Dist: importlib-resources==6.5.2; python_version >= "3.9" and python_version <= "3.11" and extra == "ar6-locked"
Requires-Dist: ixmp4==0.13.1; python_version >= "3.10" and python_version < "3.13" and extra == "ar6-locked"
Requires-Dist: kiwisolver==1.4.9; python_version >= "3.10" and extra == "ar6-locked"
Requires-Dist: kiwisolver==1.4.7; python_version < "3.10" and python_version >= "3.9" and extra == "ar6-locked"
Requires-Dist: mako==1.3.10; python_version >= "3.10" and python_version < "3.13" and extra == "ar6-locked"
Requires-Dist: markdown-it-py==3.0.0; extra == "ar6-locked"
Requires-Dist: markupsafe==3.0.2; extra == "ar6-locked"
Requires-Dist: matplotlib==3.10.7; python_version >= "3.10" and extra == "ar6-locked"
Requires-Dist: matplotlib==3.9.4; python_version < "3.10" and python_version >= "3.9" and extra == "ar6-locked"
Requires-Dist: mdurl==0.1.2; extra == "ar6-locked"
Requires-Dist: mypy==1.14.0; extra == "ar6-locked"
Requires-Dist: mypy-extensions==1.1.0; extra == "ar6-locked"
Requires-Dist: numpy==2.2.6; python_version >= "3.10" and python_version < "3.12" and extra == "ar6-locked"
Requires-Dist: numpy==2.3.3; python_version >= "3.12" and extra == "ar6-locked"
Requires-Dist: numpy==2.0.2; python_version < "3.10" and python_version >= "3.9" and extra == "ar6-locked"
Requires-Dist: openpyxl==3.1.5; extra == "ar6-locked"
Requires-Dist: openscm-runner==0.13.0; extra == "ar6-locked"
Requires-Dist: openscm-units==0.6.3; extra == "ar6-locked"
Requires-Dist: packaging==24.2; extra == "ar6-locked"
Requires-Dist: pandas==2.3.3; extra == "ar6-locked"
Requires-Dist: pandas-datapackage-reader==0.18.0; extra == "ar6-locked"
Requires-Dist: pandas-indexing==0.6.3; extra == "ar6-locked"
Requires-Dist: pandas-indexing[units]==0.6.3; extra == "ar6-locked"
Requires-Dist: pandas-openscm==0.9.0; extra == "ar6-locked"
Requires-Dist: pandas-openscm[db]==0.9.0; extra == "ar6-locked"
Requires-Dist: pandera==0.26.1; python_version >= "3.10" and python_version < "3.13" and extra == "ar6-locked"
Requires-Dist: pillow==11.3.0; extra == "ar6-locked"
Requires-Dist: pint==0.24.4; python_version >= "3.9" and python_version < "3.12" and extra == "ar6-locked"
Requires-Dist: pint==0.25; python_version >= "3.12" and extra == "ar6-locked"
Requires-Dist: pint-pandas==0.7.1; extra == "ar6-locked"
Requires-Dist: platformdirs==4.3.6; extra == "ar6-locked"
Requires-Dist: ply==3.11; python_version >= "3.10" and extra == "ar6-locked"
Requires-Dist: psycopg==3.2.10; python_version >= "3.10" and python_version < "3.13" and extra == "ar6-locked"
Requires-Dist: psycopg-binary==3.2.10; python_version >= "3.10" and python_version < "3.13" and implementation_name != "pypy" and extra == "ar6-locked"
Requires-Dist: psycopg[binary]==3.2.10; python_version >= "3.10" and python_version < "3.13" and extra == "ar6-locked"
Requires-Dist: pyam-iamc==3.1.0; python_version >= "3.10" and python_version < "3.13" and extra == "ar6-locked"
Requires-Dist: pyam-iamc==1.2.0; python_version >= "3.13" and extra == "ar6-locked"
Requires-Dist: pyam-iamc==1.6.0; python_version < "3.10" and python_version >= "3.9" and extra == "ar6-locked"
Requires-Dist: pycountry==24.6.1; python_version >= "3.10" and extra == "ar6-locked"
Requires-Dist: pydantic==2.12.0; python_version >= "3.10" and python_version < "3.13" and extra == "ar6-locked"
Requires-Dist: pydantic-core==2.41.1; python_version >= "3.10" and python_version < "3.13" and extra == "ar6-locked"
Requires-Dist: pydantic-settings==2.11.0; python_version >= "3.10" and python_version < "3.13" and extra == "ar6-locked"
Requires-Dist: pygments==2.19.1; extra == "ar6-locked"
Requires-Dist: pyjwt==2.10.1; python_version >= "3.9" and python_version < "3.13" and extra == "ar6-locked"
Requires-Dist: pymagicc==2.1.5; extra == "ar6-locked"
Requires-Dist: pyomo==6.9.4; python_version >= "3.10" and extra == "ar6-locked"
Requires-Dist: pyparsing==3.2.5; extra == "ar6-locked"
Requires-Dist: python-dateutil==2.9.0.post0; extra == "ar6-locked"
Requires-Dist: python-dotenv==1.1.1; extra == "ar6-locked"
Requires-Dist: pytz==2025.2; extra == "ar6-locked"
Requires-Dist: pyyaml==6.0.2; extra == "ar6-locked"
Requires-Dist: requests==2.32.3; extra == "ar6-locked"
Requires-Dist: rich==14.2.0; python_version >= "3.10" and python_version < "3.13" and extra == "ar6-locked"
Requires-Dist: scipy==1.15.3; python_version >= "3.10" and python_version < "3.12" and extra == "ar6-locked"
Requires-Dist: scipy==1.16.2; python_version >= "3.12" and extra == "ar6-locked"
Requires-Dist: scipy==1.13.1; python_version < "3.10" and python_version >= "3.9" and extra == "ar6-locked"
Requires-Dist: scmdata==0.18.0; extra == "ar6-locked"
Requires-Dist: seaborn==0.13.2; extra == "ar6-locked"
Requires-Dist: setuptools==75.6.0; extra == "ar6-locked"
Requires-Dist: setuptools-scm==9.2.0; (python_version < "3.10" and python_version >= "3.9" or python_version >= "3.13") and extra == "ar6-locked"
Requires-Dist: shellingham==1.5.4; python_version >= "3.10" and python_version < "3.13" and extra == "ar6-locked"
Requires-Dist: silicone==1.3.0; extra == "ar6-locked"
Requires-Dist: six==1.17.0; extra == "ar6-locked"
Requires-Dist: sniffio==1.3.1; extra == "ar6-locked"
Requires-Dist: sqlalchemy==2.0.44; python_version >= "3.10" and python_version < "3.13" and extra == "ar6-locked"
Requires-Dist: sqlalchemy-utils==0.42.0; python_version >= "3.10" and python_version < "3.13" and extra == "ar6-locked"
Requires-Dist: sqlalchemy[mypy]==2.0.44; python_version >= "3.10" and python_version < "3.13" and extra == "ar6-locked"
Requires-Dist: starlette==0.48.0; python_version >= "3.10" and python_version < "3.13" and extra == "ar6-locked"
Requires-Dist: toml==0.10.2; extra == "ar6-locked"
Requires-Dist: tomli==2.3.0; python_version >= "3.9" and python_version < "3.11" and extra == "ar6-locked"
Requires-Dist: tqdm==4.67.1; extra == "ar6-locked"
Requires-Dist: typeguard==4.4.4; python_version >= "3.10" and python_version < "3.13" and extra == "ar6-locked"
Requires-Dist: typer==0.19.2; python_version >= "3.10" and python_version < "3.13" and extra == "ar6-locked"
Requires-Dist: typing-extensions==4.15.0; extra == "ar6-locked"
Requires-Dist: typing-inspect==0.9.0; python_version >= "3.10" and python_version < "3.13" and extra == "ar6-locked"
Requires-Dist: typing-inspection==0.4.2; python_version >= "3.10" and python_version < "3.13" and extra == "ar6-locked"
Requires-Dist: tzdata==2025.2; extra == "ar6-locked"
Requires-Dist: urllib3==2.3.0; extra == "ar6-locked"
Requires-Dist: versioneer==0.29; extra == "ar6-locked"
Requires-Dist: wquantiles==0.6; python_version >= "3.10" and python_version < "3.13" and extra == "ar6-locked"
Requires-Dist: wrapt==1.17.3; extra == "ar6-locked"
Requires-Dist: xarray==2025.6.1; python_version >= "3.10" and python_version < "3.12" and extra == "ar6-locked"
Requires-Dist: xarray==2025.10.1; python_version >= "3.12" and extra == "ar6-locked"
Requires-Dist: xarray==2024.7.0; python_version == "3.9" and extra == "ar6-locked"
Requires-Dist: xlrd==2.0.2; extra == "ar6-locked"
Requires-Dist: xlsxwriter==3.2.9; python_version >= "3.9" and python_version < "3.13" and extra == "ar6-locked"
Requires-Dist: zipp==3.23.0; (python_version < "3.10" and python_version >= "3.9" or python_version >= "3.13") and extra == "ar6-locked"
Provides-Extra: cmip7scenariomip-locked
Requires-Dist: attrs==24.3.0; extra == "cmip7scenariomip-locked"
Requires-Dist: deprecated==1.2.18; extra == "cmip7scenariomip-locked"
Requires-Dist: numpy==2.2.6; python_version >= "3.10" and python_version < "3.12" and extra == "cmip7scenariomip-locked"
Requires-Dist: numpy==2.3.3; python_version >= "3.12" and extra == "cmip7scenariomip-locked"
Requires-Dist: numpy==2.0.2; python_version < "3.10" and python_version >= "3.9" and extra == "cmip7scenariomip-locked"
Requires-Dist: pandas==2.3.3; extra == "cmip7scenariomip-locked"
Requires-Dist: pandas-indexing==0.6.3; extra == "cmip7scenariomip-locked"
Requires-Dist: python-dateutil==2.9.0.post0; extra == "cmip7scenariomip-locked"
Requires-Dist: pytz==2025.2; extra == "cmip7scenariomip-locked"
Requires-Dist: six==1.17.0; extra == "cmip7scenariomip-locked"
Requires-Dist: tzdata==2025.2; extra == "cmip7scenariomip-locked"
Requires-Dist: wrapt==1.17.3; extra == "cmip7scenariomip-locked"
Provides-Extra: progress-locked
Requires-Dist: colorama==0.4.6; extra == "progress-locked"
Requires-Dist: tqdm==4.67.1; extra == "progress-locked"
Provides-Extra: full-locked
Requires-Dist: alembic==1.16.5; python_version >= "3.10" and python_version < "3.13" and extra == "full-locked"
Requires-Dist: aneris-iamc==0.4.2; python_version >= "3.10" and extra == "full-locked"
Requires-Dist: annotated-types==0.7.0; python_version >= "3.10" and python_version < "3.13" and extra == "full-locked"
Requires-Dist: anyio==4.8.0; extra == "full-locked"
Requires-Dist: attrs==24.3.0; extra == "full-locked"
Requires-Dist: certifi==2024.12.14; extra == "full-locked"
Requires-Dist: cftime==1.6.4.post1; extra == "full-locked"
Requires-Dist: charset-normalizer==3.4.1; extra == "full-locked"
Requires-Dist: click==8.1.8; extra == "full-locked"
Requires-Dist: colorama==0.4.6; extra == "full-locked"
Requires-Dist: contourpy==1.3.2; python_version >= "3.10" and python_version < "3.12" and extra == "full-locked"
Requires-Dist: contourpy==1.3.3; python_version >= "3.12" and extra == "full-locked"
Requires-Dist: contourpy==1.3.0; python_version < "3.10" and python_version >= "3.9" and extra == "full-locked"
Requires-Dist: cycler==0.12.1; extra == "full-locked"
Requires-Dist: deprecated==1.2.18; extra == "full-locked"
Requires-Dist: et-xmlfile==2.0.0; extra == "full-locked"
Requires-Dist: exceptiongroup==1.3.0; python_version >= "3.9" and python_version < "3.11" and extra == "full-locked"
Requires-Dist: f90nml==1.5; extra == "full-locked"
Requires-Dist: fastapi==0.118.3; python_version >= "3.10" and python_version < "3.13" and extra == "full-locked"
Requires-Dist: filelock==3.20.0; python_version >= "3.10" and extra == "full-locked"
Requires-Dist: filelock==3.19.1; python_version < "3.10" and python_version >= "3.9" and extra == "full-locked"
Requires-Dist: flexcache==0.3; extra == "full-locked"
Requires-Dist: flexparser==0.4; extra == "full-locked"
Requires-Dist: fonttools==4.60.1; extra == "full-locked"
Requires-Dist: globalwarmingpotentials==0.11.1; extra == "full-locked"
Requires-Dist: greenlet==3.2.4; python_version >= "3.10" and python_version < "3.13" and (platform_machine == "win32" or platform_machine == "WIN32" or platform_machine == "AMD64" or platform_machine == "amd64" or platform_machine == "x86_64" or platform_machine == "ppc64le" or platform_machine == "aarch64") and extra == "full-locked"
Requires-Dist: h11==0.14.0; extra == "full-locked"
Requires-Dist: h2==4.3.0; python_version >= "3.9" and python_version < "3.13" and extra == "full-locked"
Requires-Dist: hpack==4.1.0; python_version >= "3.9" and python_version < "3.13" and extra == "full-locked"
Requires-Dist: httpcore==1.0.7; extra == "full-locked"
Requires-Dist: httpx==0.28.1; extra == "full-locked"
Requires-Dist: httpx[http2]==0.28.1; python_version >= "3.9" and python_version < "3.13" and extra == "full-locked"
Requires-Dist: hyperframe==6.1.0; python_version >= "3.9" and python_version < "3.13" and extra == "full-locked"
Requires-Dist: iam-units==2025.9.12; extra == "full-locked"
Requires-Dist: idna==3.10; extra == "full-locked"
Requires-Dist: importlib-metadata==8.7.0; (python_version < "3.10" and python_version >= "3.9" or python_version >= "3.13") and extra == "full-locked"
Requires-Dist: importlib-resources==6.5.2; python_version >= "3.9" and python_version <= "3.11" and extra == "full-locked"
Requires-Dist: ixmp4==0.13.1; python_version >= "3.10" and python_version < "3.13" and extra == "full-locked"
Requires-Dist: kiwisolver==1.4.9; python_version >= "3.10" and extra == "full-locked"
Requires-Dist: kiwisolver==1.4.7; python_version < "3.10" and python_version >= "3.9" and extra == "full-locked"
Requires-Dist: mako==1.3.10; python_version >= "3.10" and python_version < "3.13" and extra == "full-locked"
Requires-Dist: markdown-it-py==3.0.0; extra == "full-locked"
Requires-Dist: markupsafe==3.0.2; extra == "full-locked"
Requires-Dist: matplotlib==3.10.7; python_version >= "3.10" and extra == "full-locked"
Requires-Dist: matplotlib==3.9.4; python_version < "3.10" and python_version >= "3.9" and extra == "full-locked"
Requires-Dist: mdurl==0.1.2; extra == "full-locked"
Requires-Dist: mypy==1.14.0; extra == "full-locked"
Requires-Dist: mypy-extensions==1.1.0; extra == "full-locked"
Requires-Dist: numpy==2.2.6; python_version >= "3.10" and python_version < "3.12" and extra == "full-locked"
Requires-Dist: numpy==2.3.3; python_version >= "3.12" and extra == "full-locked"
Requires-Dist: numpy==2.0.2; python_version < "3.10" and python_version >= "3.9" and extra == "full-locked"
Requires-Dist: openpyxl==3.1.5; extra == "full-locked"
Requires-Dist: openscm-runner==0.13.0; extra == "full-locked"
Requires-Dist: openscm-units==0.6.3; extra == "full-locked"
Requires-Dist: packaging==24.2; extra == "full-locked"
Requires-Dist: pandas==2.3.3; extra == "full-locked"
Requires-Dist: pandas-datapackage-reader==0.18.0; extra == "full-locked"
Requires-Dist: pandas-indexing==0.6.3; extra == "full-locked"
Requires-Dist: pandas-indexing[units]==0.6.3; extra == "full-locked"
Requires-Dist: pandas-openscm==0.9.0; extra == "full-locked"
Requires-Dist: pandas-openscm[db]==0.9.0; extra == "full-locked"
Requires-Dist: pandera==0.26.1; python_version >= "3.10" and python_version < "3.13" and extra == "full-locked"
Requires-Dist: pillow==11.3.0; extra == "full-locked"
Requires-Dist: pint==0.24.4; python_version >= "3.9" and python_version < "3.12" and extra == "full-locked"
Requires-Dist: pint==0.25; python_version >= "3.12" and extra == "full-locked"
Requires-Dist: pint-pandas==0.7.1; extra == "full-locked"
Requires-Dist: platformdirs==4.3.6; extra == "full-locked"
Requires-Dist: ply==3.11; python_version >= "3.10" and extra == "full-locked"
Requires-Dist: psycopg==3.2.10; python_version >= "3.10" and python_version < "3.13" and extra == "full-locked"
Requires-Dist: psycopg-binary==3.2.10; python_version >= "3.10" and python_version < "3.13" and implementation_name != "pypy" and extra == "full-locked"
Requires-Dist: psycopg[binary]==3.2.10; python_version >= "3.10" and python_version < "3.13" and extra == "full-locked"
Requires-Dist: pyam-iamc==3.1.0; python_version >= "3.10" and python_version < "3.13" and extra == "full-locked"
Requires-Dist: pyam-iamc==1.2.0; python_version >= "3.13" and extra == "full-locked"
Requires-Dist: pyam-iamc==1.6.0; python_version < "3.10" and python_version >= "3.9" and extra == "full-locked"
Requires-Dist: pycountry==24.6.1; python_version >= "3.10" and extra == "full-locked"
Requires-Dist: pydantic==2.12.0; python_version >= "3.10" and python_version < "3.13" and extra == "full-locked"
Requires-Dist: pydantic-core==2.41.1; python_version >= "3.10" and python_version < "3.13" and extra == "full-locked"
Requires-Dist: pydantic-settings==2.11.0; python_version >= "3.10" and python_version < "3.13" and extra == "full-locked"
Requires-Dist: pygments==2.19.1; extra == "full-locked"
Requires-Dist: pyjwt==2.10.1; python_version >= "3.9" and python_version < "3.13" and extra == "full-locked"
Requires-Dist: pymagicc==2.1.5; extra == "full-locked"
Requires-Dist: pyomo==6.9.4; python_version >= "3.10" and extra == "full-locked"
Requires-Dist: pyparsing==3.2.5; extra == "full-locked"
Requires-Dist: python-dateutil==2.9.0.post0; extra == "full-locked"
Requires-Dist: python-dotenv==1.1.1; extra == "full-locked"
Requires-Dist: pytz==2025.2; extra == "full-locked"
Requires-Dist: pyyaml==6.0.2; extra == "full-locked"
Requires-Dist: requests==2.32.3; extra == "full-locked"
Requires-Dist: rich==14.2.0; python_version >= "3.10" and python_version < "3.13" and extra == "full-locked"
Requires-Dist: scipy==1.15.3; python_version >= "3.10" and python_version < "3.12" and extra == "full-locked"
Requires-Dist: scipy==1.16.2; python_version >= "3.12" and extra == "full-locked"
Requires-Dist: scipy==1.13.1; python_version < "3.10" and python_version >= "3.9" and extra == "full-locked"
Requires-Dist: scmdata==0.18.0; extra == "full-locked"
Requires-Dist: seaborn==0.13.2; extra == "full-locked"
Requires-Dist: setuptools==75.6.0; extra == "full-locked"
Requires-Dist: setuptools-scm==9.2.0; (python_version < "3.10" and python_version >= "3.9" or python_version >= "3.13") and extra == "full-locked"
Requires-Dist: shellingham==1.5.4; python_version >= "3.10" and python_version < "3.13" and extra == "full-locked"
Requires-Dist: silicone==1.3.0; extra == "full-locked"
Requires-Dist: six==1.17.0; extra == "full-locked"
Requires-Dist: sniffio==1.3.1; extra == "full-locked"
Requires-Dist: sqlalchemy==2.0.44; python_version >= "3.10" and python_version < "3.13" and extra == "full-locked"
Requires-Dist: sqlalchemy-utils==0.42.0; python_version >= "3.10" and python_version < "3.13" and extra == "full-locked"
Requires-Dist: sqlalchemy[mypy]==2.0.44; python_version >= "3.10" and python_version < "3.13" and extra == "full-locked"
Requires-Dist: starlette==0.48.0; python_version >= "3.10" and python_version < "3.13" and extra == "full-locked"
Requires-Dist: toml==0.10.2; extra == "full-locked"
Requires-Dist: tomli==2.3.0; python_version >= "3.9" and python_version < "3.11" and extra == "full-locked"
Requires-Dist: tqdm==4.67.1; extra == "full-locked"
Requires-Dist: typeguard==4.4.4; python_version >= "3.10" and python_version < "3.13" and extra == "full-locked"
Requires-Dist: typer==0.19.2; python_version >= "3.10" and python_version < "3.13" and extra == "full-locked"
Requires-Dist: typing-extensions==4.15.0; extra == "full-locked"
Requires-Dist: typing-inspect==0.9.0; python_version >= "3.10" and python_version < "3.13" and extra == "full-locked"
Requires-Dist: typing-inspection==0.4.2; python_version >= "3.10" and python_version < "3.13" and extra == "full-locked"
Requires-Dist: tzdata==2025.2; extra == "full-locked"
Requires-Dist: urllib3==2.3.0; extra == "full-locked"
Requires-Dist: versioneer==0.29; extra == "full-locked"
Requires-Dist: wquantiles==0.6; python_version >= "3.10" and python_version < "3.13" and extra == "full-locked"
Requires-Dist: wrapt==1.17.3; extra == "full-locked"
Requires-Dist: xarray==2025.6.1; python_version >= "3.10" and python_version < "3.12" and extra == "full-locked"
Requires-Dist: xarray==2025.10.1; python_version >= "3.12" and extra == "full-locked"
Requires-Dist: xarray==2024.7.0; python_version == "3.9" and extra == "full-locked"
Requires-Dist: xlrd==2.0.2; extra == "full-locked"
Requires-Dist: xlsxwriter==3.2.9; python_version >= "3.9" and python_version < "3.13" and extra == "full-locked"
Requires-Dist: zipp==3.23.0; (python_version < "3.10" and python_version >= "3.9" or python_version >= "3.13") and extra == "full-locked"
